app/__init__.py
app/main.py
app/transformer.py
app/utils/__init__.py
app/utils/config.py
app/utils/db_client.py
app/utils/payload_schema.py
app/utils/validator.py
tests/__init__.py
tests/test_api.py
caseChange-0.1.dist-info/METADATA
caseChange-0.1.dist-info/WHEEL
caseChange-0.1.dist-info/top_level.txt
caseChange-0.1.dist-info/RECORD
