Metadata-Version: 2.1
Name: caseChange
Version: 0.1
Requires-Python: >=3.6
Requires-Dist: fastapi>=0.68.0
Requires-Dist: uvicorn>=0.15.0
